tests/__init__.py
tests/test_basic.py
whatsapp_reality/__init__.py
whatsapp_reality/analyzer.py
whatsapp_reality/preprocessor.py
whatsapp_reality/py.typed
whatsapp_reality/data/__init__.py
whatsapp_reality-0.2.1.dist-info/licenses/LICENSE
whatsapp_reality-0.2.1.dist-info/METADATA
whatsapp_reality-0.2.1.dist-info/WHEEL
whatsapp_reality-0.2.1.dist-info/top_level.txt
whatsapp_reality-0.2.1.dist-info/RECORD
