Metadata-Version: 2.4
Name: whatsapp-reality
Version: 0.2.1
Summary: A comprehensive WhatsApp chat analysis library
Home-page: https://github.com/Abdul1028/whatsapp-reality
Author: Abdul
Author-email: rasoolas2003@gmail.com
Project-URL: Bug Tracker, https://github.com/Abdul1028/whatsapp-reality/issues
Project-URL: Documentation, https://github.com/Abdul1028/whatsapp-reality#readme
Project-URL: Source Code, https://github.com/Abdul1028/whatsapp-reality
Keywords: whatsapp chat analysis nlp sentiment emoji timeline visualization
Classifier: Development Status :: 3 - Alpha
Classifier: Intended Audience :: Developers
Classifier: License :: OSI Approved :: MIT License
Classifier: Operating System :: OS Independent
Classifier: Programming Language :: Python :: 3
Classifier: Programming Language :: Python :: 3.7
Classifier: Programming Language :: Python :: 3.8
Classifier: Programming Language :: Python :: 3.9
Classifier: Programming Language :: Python :: 3.10
Classifier: Topic :: Communications :: Chat
Classifier: Topic :: Scientific/Engineering :: Information Analysis
Classifier: Topic :: Text Processing :: General
Requires-Python: >=3.7
License-File: LICENSE
Requires-Dist: numpy>=1.19.0
Requires-Dist: pandas>=1.2.0
Requires-Dist: plotly>=5.0.0
Requires-Dist: wordcloud>=1.8.0
Requires-Dist: textblob>=0.15.3
Requires-Dist: urlextract>=1.0.0
Requires-Dist: emoji>=1.2.0
Requires-Dist: nltk>=3.6.0
Requires-Dist: scikit-learn>=0.24.0
Requires-Dist: python-dateutil>=2.8.0
Requires-Dist: matplotlib>=3.3.0
Dynamic: author
Dynamic: author-email
Dynamic: classifier
Dynamic: description
Dynamic: description-content-type
Dynamic: home-page
Dynamic: keywords
Dynamic: license-file
Dynamic: project-url
Dynamic: requires-dist
Dynamic: requires-python
Dynamic: summary
